sorting_srabah/__init__.py
sorting_srabah/bubble_sort.py
sorting_srabah/help_menu.py
sorting_srabah/insertion_sort.py
sorting_srabah/quick_sort.py
sorting_srabah/selection_sort.py
sorting_srabah-0.1.dist-info/LICENSE
sorting_srabah-0.1.dist-info/METADATA
sorting_srabah-0.1.dist-info/WHEEL
sorting_srabah-0.1.dist-info/top_level.txt
sorting_srabah-0.1.dist-info/RECORD
