Metadata-Version: 2.1
Name: sorting-srabah
Version: 0.1
Summary: The sorting app ever
Home-page: http://github.com/storborg/funniest
Author: Sarah Rabah
Author-email: sarahmrabah@gmail.com
License: MIT
Platform: UNKNOWN
